LICENSE
README.md
requirements.txt
setup.cfg
setup.py
.idea/vcs.xml
.idea/workspace.xml
torrs_hammers/__init__.py
torrs_hammers/ascii_image.txt
torrs_hammers/batman.jpg
torrs_hammers/car.jpg
torrs_hammers/car.png
torrs_hammers/car.svg
torrs_hammers/images_matrix_plot.py
torrs_hammers/notifications.py
torrs_hammers/plotting.py
torrs_hammers/print_ascii.py
torrs_hammers/thammer.jpg
torrs_hammers/thammer1.png
torrs_hammers/time.py
torrs_hammers/tools.py
torrs_hammers.egg-info/PKG-INFO
torrs_hammers.egg-info/SOURCES.txt
torrs_hammers.egg-info/dependency_links.txt
torrs_hammers.egg-info/not-zip-safe
torrs_hammers.egg-info/top_level.txt
torrs_hammers/beta/__init__.py
torrs_hammers/beta/dash_example.py