Metadata-Version: 2.1
Name: torrs-hammers
Version: 0.2.3
Summary: useful tools
Home-page: https://github.com/PyTorr/torrs_hammers/archive/refs/tags/v02.tar.gz
Author: PyTorr
Author-email: 
License: MIT
Platform: UNKNOWN
